{
  "dpithedataprocessinginterfaceformodernnetworks": [
    "@inproceedings{DBLP:conf/cidr/AlonsoBPSSST0W019,\n",
    "  author    = {Gustavo Alonso and\n",
    "               Carsten Binnig and\n",
    "               Ippokratis Pandis and\n",
    "               Kenneth Salem and\n",
    "               Jan Skrzypczak and\n",
    "               Ryan Stutsman and\n",
    "               Lasse Thostrup and\n",
    "               Tianzheng Wang and\n",
    "               Zeke Wang and\n",
    "               Tobias Ziegler},\n",
    "  title     = {{DPI:} The Data Processing Interface for Modern Networks},\n",
    "  booktitle = {{CIDR} 2019, 9th Biennial Conference on Innovative Data Systems Research,\n",
    "               Asilomar, CA, USA, January 13-16, 2019, Online Proceedings},\n",
    "  publisher = {www.cidrdb.org},\n",
    "  year      = {2019},\n",
    "  url       = {http://cidrdb.org/cidr2019/papers/p11-alonso-cidr19.pdf},\n",
    "  timestamp = {Thu, 12 Mar 2020 00:00:00 +0100},\n",
    "  biburl    = {https://dblp.org/rec/conf/cidr/AlonsoBPSSST0W019.bib},\n",
    "  bibsource = {dblp computer science bibliography, https://dblp.org}\n",
    "}\n"
  ],
  "oligoarchiveusingdnainthedbmsstoragehierarchy": [
    "\n",
    "@inproceedings{DBLP:conf/cidr/AppuswamyBBAMFM19,\n",
    "  author    = {Raja Appuswamy and\n",
    "               Kevin Le Brigand and\n",
    "               Pascal Barbry and\n",
    "               Marc Antonini and\n",
    "               Olivier Madderson and\n",
    "               Paul Freemont and\n",
    "               James McDonald and\n",
    "               Thomas Heinis},\n",
    "  title     = {OligoArchive: Using {DNA} in the {DBMS} storage hierarchy},\n",
    "  booktitle = {{CIDR} 2019, 9th Biennial Conference on Innovative Data Systems Research,\n",
    "               Asilomar, CA, USA, January 13-16, 2019, Online Proceedings},\n",
    "  publisher = {www.cidrdb.org},\n",
    "  year      = {2019},\n",
    "  url       = {http://cidrdb.org/cidr2019/papers/p98-appuswamy-cidr19.pdf},\n",
    "  timestamp = {Thu, 12 Mar 2020 00:00:00 +0100},\n",
    "  biburl    = {https://dblp.org/rec/conf/cidr/AppuswamyBBAMFM19.bib},\n",
    "  bibsource = {dblp computer science bibliography, https://dblp.org}\n",
    "}\n"
  ],
  "automatedperformancemanagementforthebigdatastack": [
    "\n",
    "@inproceedings{DBLP:conf/cidr/ArvanitisBCPSW19,\n",
    "  author    = {Anastasios Arvanitis and\n",
    "               Shivnath Babu and\n",
    "               Eric Chu and\n",
    "               Adrian Popescu and\n",
    "               Alkis Simitsis and\n",
    "               Kevin Wilkinson},\n",
    "  title     = {Automated Performance Management for the Big Data Stack},\n",
    "  booktitle = {{CIDR} 2019, 9th Biennial Conference on Innovative Data Systems Research,\n",
    "               Asilomar, CA, USA, January 13-16, 2019, Online Proceedings},\n",
    "  publisher = {www.cidrdb.org},\n",
    "  year      = {2019},\n",
    "  url       = {http://cidrdb.org/cidr2019/papers/p150-arvanitis-cidr19.pdf},\n",
    "  timestamp = {Thu, 12 Mar 2020 00:00:00 +0100},\n",
    "  biburl    = {https://dblp.org/rec/conf/cidr/ArvanitisBCPSW19.bib},\n",
    "  bibsource = {dblp computer science bibliography, https://dblp.org}\n",
    "}\n"
  ],
  "serverlesseventstreamprocessingovervirtualactors": [
    "\n",
    "@inproceedings{DBLP:conf/cidr/Bernstein19,\n",
    "  author    = {Philip A. Bernstein and\n",
    "               Todd Porter and\n",
    "               Rahul Potharaju and\n",
    "               Alejandro Z. Tomsic and\n",
    "               Shivaram Venkataraman and\n",
    "               Wentao Wu},\n",
    "  title     = {Serverless Event-Stream Processing over Virtual Actors},\n",
    "  booktitle = {{CIDR} 2019, 9th Biennial Conference on Innovative Data Systems Research,\n",
    "               Asilomar, CA, USA, January 13-16, 2019, Online Proceedings},\n",
    "  publisher = {www.cidrdb.org},\n",
    "  year      = {2019},\n",
    "  url       = {http://cidrdb.org/cidr2019/gongshow/abstracts/cidr2019\\_79.pdf},\n",
    "  timestamp = {Thu, 12 Mar 2020 00:00:00 +0100},\n",
    "  biburl    = {https://dblp.org/rec/conf/cidr/Bernstein19.bib},\n",
    "  bibsource = {dblp computer science bibliography, https://dblp.org}\n",
    "}\n"
  ],
  "dbchexinteractiveexplorationofdataandschemachange": [
    "\n",
    "@inproceedings{DBLP:conf/cidr/BleifussBKNS19,\n",
    "  author    = {Tobias Bleifu{\\ss} and\n",
    "               Leon Bornemann and\n",
    "               Dmitri V. Kalashnikov and\n",
    "               Felix Naumann and\n",
    "               Divesh Srivastava},\n",
    "  title     = {DBChEx: Interactive Exploration of Data and Schema Change},\n",
    "  booktitle = {{CIDR} 2019, 9th Biennial Conference on Innovative Data Systems Research,\n",
    "               Asilomar, CA, USA, January 13-16, 2019, Online Proceedings},\n",
    "  publisher = {www.cidrdb.org},\n",
    "  year      = {2019},\n",
    "  url       = {http://cidrdb.org/cidr2019/papers/p65-bleifuss-cidr19.pdf},\n",
    "  timestamp = {Thu, 12 Mar 2020 00:00:00 +0100},\n",
    "  biburl    = {https://dblp.org/rec/conf/cidr/BleifussBKNS19.bib},\n",
    "  bibsource = {dblp computer science bibliography, https://dblp.org}\n",
    "}\n"
  ],
  "exploitinglatentinformationinrelationaldatabasesviawordembeddingandapplicationtodegreesofdisclosure": [
    "\n",
    "@inproceedings{DBLP:conf/cidr/BordawekarS19,\n",
    "  author    = {Rajesh Bordawekar and\n",
    "               Oded Shmueli},\n",
    "  title     = {Exploiting Latent Information in Relational Databases via Word Embedding\n",
    "               and Application to Degrees of Disclosure},\n",
    "  booktitle = {{CIDR} 2019, 9th Biennial Conference on Innovative Data Systems Research,\n",
    "               Asilomar, CA, USA, January 13-16, 2019, Online Proceedings},\n",
    "  publisher = {www.cidrdb.org},\n",
    "  year      = {2019},\n",
    "  url       = {http://cidrdb.org/cidr2019/papers/p27-bordawekar-cidr19.pdf},\n",
    "  timestamp = {Thu, 12 Mar 2020 00:00:00 +0100},\n",
    "  biburl    = {https://dblp.org/rec/conf/cidr/BordawekarS19.bib},\n",
    "  bibsource = {dblp computer science bibliography, https://dblp.org}\n",
    "}\n"
  ],
  "arqueryhallucinatinganalyticsoverrealworlddatausingaugmentedreality": [
    "\n",
    "@inproceedings{DBLP:conf/cidr/Burley019,\n",
    "  author    = {Codi J. Burley and\n",
    "               Arnab Nandi},\n",
    "  title     = {ARQuery: Hallucinating Analytics over Real-World Data using Augmented\n",
    "               Reality},\n",
    "  booktitle = {{CIDR} 2019, 9th Biennial Conference on Innovative Data Systems Research,\n",
    "               Asilomar, CA, USA, January 13-16, 2019, Online Proceedings},\n",
    "  publisher = {www.cidrdb.org},\n",
    "  year      = {2019},\n",
    "  url       = {http://cidrdb.org/cidr2019/papers/p93-burley-cidr19.pdf},\n",
    "  timestamp = {Thu, 12 Mar 2020 00:00:00 +0100},\n",
    "  biburl    = {https://dblp.org/rec/conf/cidr/Burley019.bib},\n",
    "  bibsource = {dblp computer science bibliography, https://dblp.org}\n",
    "}\n"
  ],
  "callingaserverlessfunctionfromacontainerbasedsystemwhythisfad": [
    "\n",
    "@inproceedings{DBLP:conf/cidr/Bussler19,\n",
    "  author    = {Christoph Bussler},\n",
    "  title     = {Calling a Server-Less Function from a Container-Based System: Why\n",
    "               This Fad?},\n",
    "  booktitle = {{CIDR} 2019, 9th Biennial Conference on Innovative Data Systems Research,\n",
    "               Asilomar, CA, USA, January 13-16, 2019, Online Proceedings},\n",
    "  publisher = {www.cidrdb.org},\n",
    "  year      = {2019},\n",
    "  url       = {http://cidrdb.org/cidr2019/gongshow/abstracts/cidr2019\\_51.pdf},\n",
    "  timestamp = {Thu, 12 Mar 2020 00:00:00 +0100},\n",
    "  biburl    = {https://dblp.org/rec/conf/cidr/Bussler19.bib},\n",
    "  bibsource = {dblp computer science bibliography, https://dblp.org}\n",
    "}\n"
  ],
  "diversityoflsmtreeshapes": [
    "\n",
    "@inproceedings{DBLP:conf/cidr/Callaghan19,\n",
    "  author    = {Mark Callaghan},\n",
    "  title     = {Diversity of {LSM} tree shapes},\n",
    "  booktitle = {{CIDR} 2019, 9th Biennial Conference on Innovative Data Systems Research,\n",
    "               Asilomar, CA, USA, January 13-16, 2019, Online Proceedings},\n",
    "  publisher = {www.cidrdb.org},\n",
    "  year      = {2019},\n",
    "  url       = {http://cidrdb.org/cidr2019/gongshow/abstracts/cidr2019\\_136.pdf},\n",
    "  timestamp = {Thu, 12 Mar 2020 00:00:00 +0100},\n",
    "  biburl    = {https://dblp.org/rec/conf/cidr/Callaghan19.bib},\n",
    "  bibsource = {dblp computer science bibliography, https://dblp.org}\n",
    "}\n"
  ],
  "hardwareconsciousqueryprocessingingpuacceleratedanalyticalengines": [
    "\n",
    "@inproceedings{DBLP:conf/cidr/ChrysogelosSA19,\n",
    "  author    = {Periklis Chrysogelos and\n",
    "               Panagiotis Sioulas and\n",
    "               Anastasia Ailamaki},\n",
    "  title     = {Hardware-conscious Query Processing in GPU-accelerated Analytical\n",
    "               Engines},\n",
    "  booktitle = {{CIDR} 2019, 9th Biennial Conference on Innovative Data Systems Research,\n",
    "               Asilomar, CA, USA, January 13-16, 2019, Online Proceedings},\n",
    "  publisher = {www.cidrdb.org},\n",
    "  year      = {2019},\n",
    "  url       = {http://cidrdb.org/cidr2019/papers/p127-chrysogelos-cidr19.pdf},\n",
    "  timestamp = {Thu, 12 Mar 2020 00:00:00 +0100},\n",
    "  biburl    = {https://dblp.org/rec/conf/cidr/ChrysogelosSA19.bib},\n",
    "  bibsource = {dblp computer science bibliography, https://dblp.org}\n",
    "}\n"
  ],
  "nulldbinstantaneouslyansweringanyolapquery": [
    "\n",
    "@inproceedings{DBLP:conf/cidr/Crotty19,\n",
    "  author    = {Andrew Crotty},\n",
    "  title     = {NullDB: Instantaneously Answering Any {OLAP} Query},\n",
    "  booktitle = {{CIDR} 2019, 9th Biennial Conference on Innovative Data Systems Research,\n",
    "               Asilomar, CA, USA, January 13-16, 2019, Online Proceedings},\n",
    "  publisher = {www.cidrdb.org},\n",
    "  year      = {2019},\n",
    "  url       = {http://cidrdb.org/cidr2019/gongshow/abstracts/cidr2019\\_116.pdf},\n",
    "  timestamp = {Thu, 12 Mar 2020 00:00:00 +0100},\n",
    "  biburl    = {https://dblp.org/rec/conf/cidr/Crotty19.bib},\n",
    "  bibsource = {dblp computer science bibliography, https://dblp.org}\n",
    "}\n"
  ],
  "everyrowcountscombiningsketchesandsamplingforaccurategroupbyresultestimates": [
    "\n",
    "@inproceedings{DBLP:conf/cidr/Freitag019,\n",
    "  author    = {Michael J. Freitag and\n",
    "               Thomas Neumann},\n",
    "  title     = {Every Row Counts: Combining Sketches and Sampling for Accurate Group-By\n",
    "               Result Estimates},\n",
    "  booktitle = {{CIDR} 2019, 9th Biennial Conference on Innovative Data Systems Research,\n",
    "               Asilomar, CA, USA, January 13-16, 2019, Online Proceedings},\n",
    "  publisher = {www.cidrdb.org},\n",
    "  year      = {2019},\n",
    "  url       = {http://cidrdb.org/cidr2019/papers/p23-freitag-cidr19.pdf},\n",
    "  timestamp = {Thu, 12 Mar 2020 00:00:00 +0100},\n",
    "  biburl    = {https://dblp.org/rec/conf/cidr/Freitag019.bib},\n",
    "  bibsource = {dblp computer science bibliography, https://dblp.org}\n",
    "}\n"
  ],
  "veritassharedverifiabledatabasesandtablesinthecloud": [
    "\n",
    "@inproceedings{DBLP:conf/cidr/GehrkeAAAHHKKRS19,\n",
    "  author    = {Johannes Gehrke and\n",
    "               Lindsay Allen and\n",
    "               Panagiotis Antonopoulos and\n",
    "               Arvind Arasu and\n",
    "               Joachim Hammer and\n",
    "               James Hunter and\n",
    "               Raghav Kaushik and\n",
    "               Donald Kossmann and\n",
    "               Ravi Ramamurthy and\n",
    "               Srinath T. V. Setty and\n",
    "               Jakub Szymaszek and\n",
    "               Alexander van Renen and\n",
    "               Jonathan Lee and\n",
    "               Ramarathnam Venkatesan},\n",
    "  title     = {Veritas: Shared Verifiable Databases and Tables in the Cloud},\n",
    "  booktitle = {{CIDR} 2019, 9th Biennial Conference on Innovative Data Systems Research,\n",
    "               Asilomar, CA, USA, January 13-16, 2019, Online Proceedings},\n",
    "  publisher = {www.cidrdb.org},\n",
    "  year      = {2019},\n",
    "  url       = {http://cidrdb.org/cidr2019/papers/p111-gehrke-cidr19.pdf},\n",
    "  timestamp = {Tue, 24 Nov 2020 00:00:00 +0100},\n",
    "  biburl    = {https://dblp.org/rec/conf/cidr/GehrkeAAAHHKKRS19.bib},\n",
    "  bibsource = {dblp computer science bibliography, https://dblp.org}\n",
    "}\n"
  ],
  "querydrivendatacleaningforexploratoryqueries": [
    "\n",
    "@inproceedings{DBLP:conf/cidr/Giannakopoulou19,\n",
    "  author    = {Stella Giannakopoulou},\n",
    "  title     = {Query-Driven Data Cleaning for Exploratory Queries},\n",
    "  booktitle = {{CIDR} 2019, 9th Biennial Conference on Innovative Data Systems Research,\n",
    "               Asilomar, CA, USA, January 13-16, 2019, Online Proceedings},\n",
    "  publisher = {www.cidrdb.org},\n",
    "  year      = {2019},\n",
    "  url       = {http://cidrdb.org/cidr2019/gongshow/abstracts/cidr2019\\_138.pdf},\n",
    "  timestamp = {Thu, 12 Mar 2020 00:00:00 +0100},\n",
    "  biburl    = {https://dblp.org/rec/conf/cidr/Giannakopoulou19.bib},\n",
    "  bibsource = {dblp computer science bibliography, https://dblp.org}\n",
    "}\n"
  ],
  "theishaveitidentityimmutabilityidempotenceandinterchangeabilityformthebackboneofdistributedcomputing": [
    "\n",
    "@inproceedings{DBLP:conf/cidr/Helland19,\n",
    "  author    = {Pat Helland},\n",
    "  title     = {The I's Have It: Identity, Immutability, Idempotence, and Interchangeability\n",
    "               Form the Backbone of Distributed Computing},\n",
    "  booktitle = {{CIDR} 2019, 9th Biennial Conference on Innovative Data Systems Research,\n",
    "               Asilomar, CA, USA, January 13-16, 2019, Online Proceedings},\n",
    "  publisher = {www.cidrdb.org},\n",
    "  year      = {2019},\n",
    "  url       = {http://cidrdb.org/cidr2019/gongshow/abstracts/cidr2019\\_161.pdf},\n",
    "  timestamp = {Thu, 12 Mar 2020 00:00:00 +0100},\n",
    "  biburl    = {https://dblp.org/rec/conf/cidr/Helland19.bib},\n",
    "  bibsource = {dblp computer science bibliography, https://dblp.org}\n",
    "}\n"
  ],
  "serverlesscomputingonestepforwardtwostepsback": [
    "\n",
    "@inproceedings{DBLP:conf/cidr/HellersteinFGSS19,\n",
    "  author    = {Joseph M. Hellerstein and\n",
    "               Jose M. Faleiro and\n",
    "               Joseph Gonzalez and\n",
    "               Johann Schleier{-}Smith and\n",
    "               Vikram Sreekanti and\n",
    "               Alexey Tumanov and\n",
    "               Chenggang Wu},\n",
    "  title     = {Serverless Computing: One Step Forward, Two Steps Back},\n",
    "  booktitle = {{CIDR} 2019, 9th Biennial Conference on Innovative Data Systems Research,\n",
    "               Asilomar, CA, USA, January 13-16, 2019, Online Proceedings},\n",
    "  publisher = {www.cidrdb.org},\n",
    "  year      = {2019},\n",
    "  url       = {http://cidrdb.org/cidr2019/papers/p119-hellerstein-cidr19.pdf},\n",
    "  timestamp = {Tue, 18 Aug 2020 01:00:00 +0200},\n",
    "  biburl    = {https://dblp.org/rec/conf/cidr/HellersteinFGSS19.bib},\n",
    "  bibsource = {dblp computer science bibliography, https://dblp.org}\n",
    "}\n"
  ],
  "designcontinuumsandthepathtowardselfdesigningkeyvaluestoresthatknowandlearn": [
    "\n",
    "@inproceedings{DBLP:conf/cidr/IdreosDQAHRLJGL19,\n",
    "  author    = {Stratos Idreos and\n",
    "               Niv Dayan and\n",
    "               Wilson Qin and\n",
    "               Mali Akmanalp and\n",
    "               Sophie Hilgard and\n",
    "               Andrew Ross and\n",
    "               James Lennon and\n",
    "               Varun Jain and\n",
    "               Harshita Gupta and\n",
    "               David Li and\n",
    "               Zichen Zhu},\n",
    "  title     = {Design Continuums and the Path Toward Self-Designing Key-Value Stores\n",
    "               that Know and Learn},\n",
    "  booktitle = {{CIDR} 2019, 9th Biennial Conference on Innovative Data Systems Research,\n",
    "               Asilomar, CA, USA, January 13-16, 2019, Online Proceedings},\n",
    "  publisher = {www.cidrdb.org},\n",
    "  year      = {2019},\n",
    "  url       = {http://cidrdb.org/cidr2019/papers/p143-idreos-cidr19.pdf},\n",
    "  timestamp = {Thu, 12 Mar 2020 00:00:00 +0100},\n",
    "  biburl    = {https://dblp.org/rec/conf/cidr/IdreosDQAHRLJGL19.bib},\n",
    "  bibsource = {dblp computer science bibliography, https://dblp.org}\n",
    "}\n"
  ],
  "datasetrelationshipmanagement": [
    "\n",
    "@inproceedings{DBLP:conf/cidr/IvesZHZ19,\n",
    "  author    = {Zack Ives and\n",
    "               Yi Zhang and\n",
    "               Soonbo Han and\n",
    "               Nan Zheng},\n",
    "  title     = {Dataset Relationship Management},\n",
    "  booktitle = {{CIDR} 2019, 9th Biennial Conference on Innovative Data Systems Research,\n",
    "               Asilomar, CA, USA, January 13-16, 2019, Online Proceedings},\n",
    "  publisher = {www.cidrdb.org},\n",
    "  year      = {2019},\n",
    "  url       = {http://cidrdb.org/cidr2019/papers/p55-ives-cidr19.pdf},\n",
    "  timestamp = {Thu, 12 Mar 2020 00:00:00 +0100},\n",
    "  biburl    = {https://dblp.org/rec/conf/cidr/IvesZHZ19.bib},\n",
    "  bibsource = {dblp computer science bibliography, https://dblp.org}\n",
    "}\n"
  ],
  "databaseagnosticworkloadmanagement": [
    "\n",
    "@inproceedings{DBLP:conf/cidr/JainYCH19,\n",
    "  author    = {Shrainik Jain and\n",
    "               Jiaqi Yan and\n",
    "               Thierry Cruanes and\n",
    "               Bill Howe},\n",
    "  title     = {Database-Agnostic Workload Management},\n",
    "  booktitle = {{CIDR} 2019, 9th Biennial Conference on Innovative Data Systems Research,\n",
    "               Asilomar, CA, USA, January 13-16, 2019, Online Proceedings},\n",
    "  publisher = {www.cidrdb.org},\n",
    "  year      = {2019},\n",
    "  url       = {http://cidrdb.org/cidr2019/papers/p110-jain-cidr19.pdf},\n",
    "  timestamp = {Thu, 12 Mar 2020 00:00:00 +0100},\n",
    "  biburl    = {https://dblp.org/rec/conf/cidr/JainYCH19.bib},\n",
    "  bibsource = {dblp computer science bibliography, https://dblp.org}\n",
    "}\n"
  ],
  "demonstrationofamultiresolutionschemamappingsystem": [
    "\n",
    "@inproceedings{DBLP:conf/cidr/JinBCJL19,\n",
    "  author    = {Zhongjun Jin and\n",
    "               Christopher Baik and\n",
    "               Michael J. Cafarella and\n",
    "               H. V. Jagadish and\n",
    "               Yuze Lou},\n",
    "  title     = {Demonstration of a Multiresolution Schema Mapping System},\n",
    "  booktitle = {{CIDR} 2019, 9th Biennial Conference on Innovative Data Systems Research,\n",
    "               Asilomar, CA, USA, January 13-16, 2019, Online Proceedings},\n",
    "  publisher = {www.cidrdb.org},\n",
    "  year      = {2019},\n",
    "  url       = {http://cidrdb.org/cidr2019/papers/p9-jin-cidr19.pdf},\n",
    "  timestamp = {Thu, 12 Mar 2020 00:00:00 +0100},\n",
    "  biburl    = {https://dblp.org/rec/conf/cidr/JinBCJL19.bib},\n",
    "  bibsource = {dblp computer science bibliography, https://dblp.org}\n",
    "}\n"
  ],
  "challengesandopportunitiesindnnbasedvideoanalyticsademonstrationoftheblazeitvideoqueryengine": [
    "\n",
    "@inproceedings{DBLP:conf/cidr/KangBZ19,\n",
    "  author    = {Daniel Kang and\n",
    "               Peter Bailis and\n",
    "               Matei Zaharia},\n",
    "  title     = {Challenges and Opportunities in DNN-Based Video Analytics: {A} Demonstration\n",
    "               of the BlazeIt Video Query Engine},\n",
    "  booktitle = {{CIDR} 2019, 9th Biennial Conference on Innovative Data Systems Research,\n",
    "               Asilomar, CA, USA, January 13-16, 2019, Online Proceedings},\n",
    "  publisher = {www.cidrdb.org},\n",
    "  year      = {2019},\n",
    "  url       = {http://cidrdb.org/cidr2019/papers/p141-kang-cidr19.pdf},\n",
    "  timestamp = {Thu, 12 Mar 2020 00:00:00 +0100},\n",
    "  biburl    = {https://dblp.org/rec/conf/cidr/KangBZ19.bib},\n",
    "  bibsource = {dblp computer science bibliography, https://dblp.org}\n",
    "}\n"
  ],
  "sqalpeladatabaseperformanceplatform": [
    "\n",
    "@inproceedings{DBLP:conf/cidr/KerstenMZK19,\n",
    "  author    = {Martin L. Kersten and\n",
    "               Stefan Manegold and\n",
    "               Ying Zhang and\n",
    "               Panos Kuoutsourakis},\n",
    "  title     = {{SQALPEL:} {A} database performance platform},\n",
    "  booktitle = {{CIDR} 2019, 9th Biennial Conference on Innovative Data Systems Research,\n",
    "               Asilomar, CA, USA, January 13-16, 2019, Online Proceedings},\n",
    "  publisher = {www.cidrdb.org},\n",
    "  year      = {2019},\n",
    "  url       = {http://cidrdb.org/cidr2019/papers/p50-kersten-cidr19.pdf},\n",
    "  timestamp = {Thu, 12 Mar 2020 00:00:00 +0100},\n",
    "  biburl    = {https://dblp.org/rec/conf/cidr/KerstenMZK19.bib},\n",
    "  bibsource = {dblp computer science bibliography, https://dblp.org}\n",
    "}\n"
  ],
  "learnedcardinalitiesestimatingcorrelatedjoinswithdeeplearning": [
    "\n",
    "@inproceedings{DBLP:conf/cidr/KipfKRLBK19,\n",
    "  author    = {Andreas Kipf and\n",
    "               Thomas Kipf and\n",
    "               Bernhard Radke and\n",
    "               Viktor Leis and\n",
    "               Peter A. Boncz and\n",
    "               Alfons Kemper},\n",
    "  title     = {Learned Cardinalities: Estimating Correlated Joins with Deep Learning},\n",
    "  booktitle = {{CIDR} 2019, 9th Biennial Conference on Innovative Data Systems Research,\n",
    "               Asilomar, CA, USA, January 13-16, 2019, Online Proceedings},\n",
    "  publisher = {www.cidrdb.org},\n",
    "  year      = {2019},\n",
    "  url       = {http://cidrdb.org/cidr2019/papers/p101-kipf-cidr19.pdf},\n",
    "  timestamp = {Thu, 12 Mar 2020 00:00:00 +0100},\n",
    "  biburl    = {https://dblp.org/rec/conf/cidr/KipfKRLBK19.bib},\n",
    "  bibsource = {dblp computer science bibliography, https://dblp.org}\n",
    "}\n"
  ],
  "architectingadifferentiallyprivatesqlengine": [
    "\n",
    "@inproceedings{DBLP:conf/cidr/KotsogiannisTMM19,\n",
    "  author    = {Ios Kotsogiannis and\n",
    "               Yuchao Tao and\n",
    "               Ashwin Machanavajjhala and\n",
    "               Gerome Miklau and\n",
    "               Michael Hay},\n",
    "  title     = {Architecting a Differentially Private {SQL} Engine},\n",
    "  booktitle = {{CIDR} 2019, 9th Biennial Conference on Innovative Data Systems Research,\n",
    "               Asilomar, CA, USA, January 13-16, 2019, Online Proceedings},\n",
    "  publisher = {www.cidrdb.org},\n",
    "  year      = {2019},\n",
    "  url       = {http://cidrdb.org/cidr2019/papers/p125-kotsogiannis-cidr19.pdf},\n",
    "  timestamp = {Thu, 12 Mar 2020 00:00:00 +0100},\n",
    "  biburl    = {https://dblp.org/rec/conf/cidr/KotsogiannisTMM19.bib},\n",
    "  bibsource = {dblp computer science bibliography, https://dblp.org}\n",
    "}\n"
  ],
  "sagedbalearneddatabasesystem": [
    "\n",
    "@inproceedings{DBLP:conf/cidr/KraskaABCKLMMN19,\n",
    "  author    = {Tim Kraska and\n",
    "               Mohammad Alizadeh and\n",
    "               Alex Beutel and\n",
    "               Ed H. Chi and\n",
    "               Ani Kristo and\n",
    "               Guillaume Leclerc and\n",
    "               Samuel Madden and\n",
    "               Hongzi Mao and\n",
    "               Vikram Nathan},\n",
    "  title     = {SageDB: {A} Learned Database System},\n",
    "  booktitle = {{CIDR} 2019, 9th Biennial Conference on Innovative Data Systems Research,\n",
    "               Asilomar, CA, USA, January 13-16, 2019, Online Proceedings},\n",
    "  publisher = {www.cidrdb.org},\n",
    "  year      = {2019},\n",
    "  url       = {http://cidrdb.org/cidr2019/papers/p117-kraska-cidr19.pdf},\n",
    "  timestamp = {Thu, 12 Mar 2020 00:00:00 +0100},\n",
    "  biburl    = {https://dblp.org/rec/conf/cidr/KraskaABCKLMMN19.bib},\n",
    "  bibsource = {dblp computer science bibliography, https://dblp.org}\n",
    "}\n"
  ],
  "deeplenstowardsavisualdatamanagementsystem": [
    "\n",
    "@inproceedings{DBLP:conf/cidr/KrishnanDE19,\n",
    "  author    = {Sanjay Krishnan and\n",
    "               Adam Dziedzic and\n",
    "               Aaron J. Elmore},\n",
    "  title     = {DeepLens: Towards a Visual Data Management System},\n",
    "  booktitle = {{CIDR} 2019, 9th Biennial Conference on Innovative Data Systems Research,\n",
    "               Asilomar, CA, USA, January 13-16, 2019, Online Proceedings},\n",
    "  publisher = {www.cidrdb.org},\n",
    "  year      = {2019},\n",
    "  url       = {http://cidrdb.org/cidr2019/papers/p40-krishnan-cidr19.pdf},\n",
    "  timestamp = {Thu, 12 Mar 2020 00:00:00 +0100},\n",
    "  biburl    = {https://dblp.org/rec/conf/cidr/KrishnanDE19.bib},\n",
    "  bibsource = {dblp computer science bibliography, https://dblp.org}\n",
    "}\n"
  ],
  "thecasefornetworkacceleratedqueryprocessing": [
    "\n",
    "@inproceedings{DBLP:conf/cidr/LernerHC19,\n",
    "  author    = {Alberto Lerner and\n",
    "               Rana Hussein and\n",
    "               Philippe Cudr{\\'{e}}{-}Mauroux},\n",
    "  title     = {The Case for Network Accelerated Query Processing},\n",
    "  booktitle = {{CIDR} 2019, 9th Biennial Conference on Innovative Data Systems Research,\n",
    "               Asilomar, CA, USA, January 13-16, 2019, Online Proceedings},\n",
    "  publisher = {www.cidrdb.org},\n",
    "  year      = {2019},\n",
    "  url       = {http://cidrdb.org/cidr2019/papers/p142-lerner-cidr19.pdf},\n",
    "  timestamp = {Thu, 12 Mar 2020 00:00:00 +0100},\n",
    "  biburl    = {https://dblp.org/rec/conf/cidr/LernerHC19.bib},\n",
    "  bibsource = {dblp computer science bibliography, https://dblp.org}\n",
    "}\n"
  ],
  "decentralizedsearchondecentralizedweb": [
    "\n",
    "@inproceedings{DBLP:conf/cidr/Lo19,\n",
    "  author    = {Eric Lo},\n",
    "  title     = {Decentralized Search on Decentralized Web},\n",
    "  booktitle = {{CIDR} 2019, 9th Biennial Conference on Innovative Data Systems Research,\n",
    "               Asilomar, CA, USA, January 13-16, 2019, Online Proceedings},\n",
    "  publisher = {www.cidrdb.org},\n",
    "  year      = {2019},\n",
    "  url       = {http://cidrdb.org/cidr2019/gongshow/abstracts/cidr2019\\_30.pdf},\n",
    "  timestamp = {Thu, 08 Oct 2020 01:00:00 +0200},\n",
    "  biburl    = {https://dblp.org/rec/conf/cidr/Lo19.bib},\n",
    "  bibsource = {dblp computer science bibliography, https://dblp.org}\n",
    "}\n"
  ],
  "towardsahandsfreequeryoptimizerthroughdeeplearning": [
    "\n",
    "@inproceedings{DBLP:conf/cidr/MarcusP19,\n",
    "  author    = {Ryan Marcus and\n",
    "               Olga Papaemmanouil},\n",
    "  title     = {Towards a Hands-Free Query Optimizer through Deep Learning},\n",
    "  booktitle = {{CIDR} 2019, 9th Biennial Conference on Innovative Data Systems Research,\n",
    "               Asilomar, CA, USA, January 13-16, 2019, Online Proceedings},\n",
    "  publisher = {www.cidrdb.org},\n",
    "  year      = {2019},\n",
    "  url       = {http://cidrdb.org/cidr2019/papers/p96-marcus-cidr19.pdf},\n",
    "  timestamp = {Thu, 12 Mar 2020 00:00:00 +0100},\n",
    "  biburl    = {https://dblp.org/rec/conf/cidr/MarcusP19.bib},\n",
    "  bibsource = {dblp computer science bibliography, https://dblp.org}\n",
    "}\n"
  ],
  "elasticinmemorytransactionprocessingformultitenantdatabasesystems": [
    "\n",
    "@inproceedings{DBLP:conf/cidr/Mirzargar19,\n",
    "  author    = {Seyedehsharareh Mirzargar},\n",
    "  title     = {Elastic In-Memory Transaction Processing for Multi-Tenant Database\n",
    "               Systems},\n",
    "  booktitle = {{CIDR} 2019, 9th Biennial Conference on Innovative Data Systems Research,\n",
    "               Asilomar, CA, USA, January 13-16, 2019, Online Proceedings},\n",
    "  publisher = {www.cidrdb.org},\n",
    "  year      = {2019},\n",
    "  url       = {http://cidrdb.org/cidr2019/gongshow/abstracts/cidr2019\\_137.pdf},\n",
    "  timestamp = {Thu, 12 Mar 2020 00:00:00 +0100},\n",
    "  biburl    = {https://dblp.org/rec/conf/cidr/Mirzargar19.bib},\n",
    "  bibsource = {dblp computer science bibliography, https://dblp.org}\n",
    "}\n"
  ],
  "bringingdatabasesuptopocketscale": [
    "\n",
    "@inproceedings{DBLP:conf/cidr/Nuessle19,\n",
    "  author    = {Carl Nuessle},\n",
    "  title     = {Bringing Databases up to Pocket-Scale},\n",
    "  booktitle = {{CIDR} 2019, 9th Biennial Conference on Innovative Data Systems Research,\n",
    "               Asilomar, CA, USA, January 13-16, 2019, Online Proceedings},\n",
    "  publisher = {www.cidrdb.org},\n",
    "  year      = {2019},\n",
    "  url       = {http://cidrdb.org/cidr2019/gongshow/abstracts/cidr2019\\_159.pdf},\n",
    "  timestamp = {Thu, 12 Mar 2020 00:00:00 +0100},\n",
    "  biburl    = {https://dblp.org/rec/conf/cidr/Nuessle19.bib},\n",
    "  bibsource = {dblp computer science bibliography, https://dblp.org}\n",
    "}\n"
  ],
  "fixeditforyouprotocolrepairusinglineagegraphs": [
    "\n",
    "@inproceedings{DBLP:conf/cidr/OldenburgZRA19,\n",
    "  author    = {Lennart Oldenburg and\n",
    "               Xiangfeng Zhu and\n",
    "               Kamala Ramasubramanian and\n",
    "               Peter Alvaro},\n",
    "  title     = {Fixed It For You: Protocol Repair Using Lineage Graphs},\n",
    "  booktitle = {{CIDR} 2019, 9th Biennial Conference on Innovative Data Systems Research,\n",
    "               Asilomar, CA, USA, January 13-16, 2019, Online Proceedings},\n",
    "  publisher = {www.cidrdb.org},\n",
    "  year      = {2019},\n",
    "  url       = {http://cidrdb.org/cidr2019/papers/p122-oldenburg-cidr19.pdf},\n",
    "  timestamp = {Thu, 12 Mar 2020 00:00:00 +0100},\n",
    "  biburl    = {https://dblp.org/rec/conf/cidr/OldenburgZRA19.bib},\n",
    "  bibsource = {dblp computer science bibliography, https://dblp.org}\n",
    "}\n"
  ],
  "cryodrillneardataprocessingindeepandcoldstoragehierarchies": [
    "\n",
    "@inproceedings{DBLP:conf/cidr/Paradies19,\n",
    "  author    = {Marcus Paradies},\n",
    "  title     = {CryoDrill: Near-Data Processing in Deep and Cold Storage Hierarchies},\n",
    "  booktitle = {{CIDR} 2019, 9th Biennial Conference on Innovative Data Systems Research,\n",
    "               Asilomar, CA, USA, January 13-16, 2019, Online Proceedings},\n",
    "  publisher = {www.cidrdb.org},\n",
    "  year      = {2019},\n",
    "  url       = {http://cidrdb.org/cidr2019/gongshow/abstracts/cidr2019\\_48.pdf},\n",
    "  timestamp = {Thu, 12 Mar 2020 00:00:00 +0100},\n",
    "  biburl    = {https://dblp.org/rec/conf/cidr/Paradies19.bib},\n",
    "  bibsource = {dblp computer science bibliography, https://dblp.org}\n",
    "}\n"
  ],
  "thrivinginthenomanslandbetweencompilersanddatabases": [
    "\n",
    "@inproceedings{DBLP:conf/cidr/PirkGP19,\n",
    "  author    = {Holger Pirk and\n",
    "               Jana Giceva and\n",
    "               Peter R. Pietzuch},\n",
    "  title     = {Thriving in the No Man's Land between Compilers and Databases},\n",
    "  booktitle = {{CIDR} 2019, 9th Biennial Conference on Innovative Data Systems Research,\n",
    "               Asilomar, CA, USA, January 13-16, 2019, Online Proceedings},\n",
    "  publisher = {www.cidrdb.org},\n",
    "  year      = {2019},\n",
    "  url       = {http://cidrdb.org/cidr2019/papers/p91-pirk-cidr19.pdf},\n",
    "  timestamp = {Thu, 12 Mar 2020 00:00:00 +0100},\n",
    "  biburl    = {https://dblp.org/rec/conf/cidr/PirkGP19.bib},\n",
    "  bibsource = {dblp computer science bibliography, https://dblp.org}\n",
    "}\n"
  ],
  "revisitingriscstyledatamanagementsystemdesign": [
    "\n",
    "@inproceedings{DBLP:conf/cidr/Porobic19,\n",
    "  author    = {Danica Porobic},\n",
    "  title     = {Revisiting RISC-style Data Management System Design},\n",
    "  booktitle = {{CIDR} 2019, 9th Biennial Conference on Innovative Data Systems Research,\n",
    "               Asilomar, CA, USA, January 13-16, 2019, Online Proceedings},\n",
    "  publisher = {www.cidrdb.org},\n",
    "  year      = {2019},\n",
    "  url       = {http://cidrdb.org/cidr2019/gongshow/abstracts/cidr2019\\_68.pdf},\n",
    "  timestamp = {Thu, 12 Mar 2020 00:00:00 +0100},\n",
    "  biburl    = {https://dblp.org/rec/conf/cidr/Porobic19.bib},\n",
    "  bibsource = {dblp computer science bibliography, https://dblp.org}\n",
    "}\n"
  ],
  "usingbotsmachinelearningpipelinestocreateamoderndatamanagementenvironment": [
    "\n",
    "@inproceedings{DBLP:conf/cidr/Ramsay19,\n",
    "  author    = {Mark Ramsay},\n",
    "  title     = {Using Bots, Machine Learning {\\&} Pipelines to create a modern data\n",
    "               management environment},\n",
    "  booktitle = {{CIDR} 2019, 9th Biennial Conference on Innovative Data Systems Research,\n",
    "               Asilomar, CA, USA, January 13-16, 2019, Online Proceedings},\n",
    "  publisher = {www.cidrdb.org},\n",
    "  year      = {2019},\n",
    "  timestamp = {Thu, 17 Jan 2019 00:00:00 +0100},\n",
    "  biburl    = {https://dblp.org/rec/conf/cidr/Ramsay19.bib},\n",
    "  bibsource = {dblp computer science bibliography, https://dblp.org}\n",
    "}\n"
  ],
  "theroleofmassivelymultitaskandweaksupervisioninsoftware": [
    "\n",
    "@inproceedings{DBLP:conf/cidr/RatnerHR19,\n",
    "  author    = {Alexander J. Ratner and\n",
    "               Braden Hancock and\n",
    "               Christopher R{\\'{e}}},\n",
    "  title     = {The Role of Massively Multi-Task and Weak Supervision in Software\n",
    "               2.0},\n",
    "  booktitle = {{CIDR} 2019, 9th Biennial Conference on Innovative Data Systems Research,\n",
    "               Asilomar, CA, USA, January 13-16, 2019, Online Proceedings},\n",
    "  publisher = {www.cidrdb.org},\n",
    "  year      = {2019},\n",
    "  url       = {http://cidrdb.org/cidr2019/papers/p58-ratner-cidr19.pdf},\n",
    "  timestamp = {Thu, 12 Mar 2020 00:00:00 +0100},\n",
    "  biburl    = {https://dblp.org/rec/conf/cidr/RatnerHR19.bib},\n",
    "  bibsource = {dblp computer science bibliography, https://dblp.org}\n",
    "}\n"
  ],
  "storingandqueryingsocialgraphdataonavarietyofdistributedsystems": [
    "\n",
    "@inproceedings{DBLP:conf/cidr/Reilly19,\n",
    "  author    = {Christine Reilly},\n",
    "  title     = {Storing and Querying Social Graph Data on a Variety of Distributed\n",
    "               Systems},\n",
    "  booktitle = {{CIDR} 2019, 9th Biennial Conference on Innovative Data Systems Research,\n",
    "               Asilomar, CA, USA, January 13-16, 2019, Online Proceedings},\n",
    "  publisher = {www.cidrdb.org},\n",
    "  year      = {2019},\n",
    "  url       = {http://cidrdb.org/cidr2019/gongshow/abstracts/cidr2019\\_95.pdf},\n",
    "  timestamp = {Thu, 12 Mar 2020 00:00:00 +0100},\n",
    "  biburl    = {https://dblp.org/rec/conf/cidr/Reilly19.bib},\n",
    "  bibsource = {dblp computer science bibliography, https://dblp.org}\n",
    "}\n"
  ],
  "serverlessfoundationsforelasticdatabasesystems": [
    "\n",
    "@inproceedings{DBLP:conf/cidr/Schleier-Smith19,\n",
    "  author    = {Johann Schleier{-}Smith},\n",
    "  title     = {Serverless Foundations for Elastic Database Systems},\n",
    "  booktitle = {{CIDR} 2019, 9th Biennial Conference on Innovative Data Systems Research,\n",
    "               Asilomar, CA, USA, January 13-16, 2019, Online Proceedings},\n",
    "  publisher = {www.cidrdb.org},\n",
    "  year      = {2019},\n",
    "  url       = {http://cidrdb.org/cidr2019/gongshow/abstracts/cidr2019\\_140.pdf},\n",
    "  timestamp = {Thu, 12 Mar 2020 00:00:00 +0100},\n",
    "  biburl    = {https://dblp.org/rec/conf/cidr/Schleier-Smith19.bib},\n",
    "  bibsource = {dblp computer science bibliography, https://dblp.org}\n",
    "}\n"
  ],
  "datawarehousesaredeadlonglivedatawarehousing": [
    "\n",
    "@inproceedings{DBLP:conf/cidr/Shah19,\n",
    "  author    = {Mehul Shah},\n",
    "  title     = {Data warehouses are dead, long live data warehousing!},\n",
    "  booktitle = {{CIDR} 2019, 9th Biennial Conference on Innovative Data Systems Research,\n",
    "               Asilomar, CA, USA, January 13-16, 2019, Online Proceedings},\n",
    "  publisher = {www.cidrdb.org},\n",
    "  year      = {2019},\n",
    "  url       = {http://cidrdb.org/cidr2019/gongshow/abstracts/cidr2019\\_152.pdf},\n",
    "  timestamp = {Thu, 12 Mar 2020 00:00:00 +0100},\n",
    "  biburl    = {https://dblp.org/rec/conf/cidr/Shah19.bib},\n",
    "  bibsource = {dblp computer science bibliography, https://dblp.org}\n",
    "}\n"
  ],
  "selectivitycomputationforinmemoryqueryoptimization": [
    "\n",
    "@inproceedings{DBLP:conf/cidr/Shin19,\n",
    "  author    = {Jun Hyung Shin and\n",
    "               Florin Rusu and\n",
    "               Alex Suhan},\n",
    "  title     = {Selectivity Computation for In-Memory Query Optimization},\n",
    "  booktitle = {{CIDR} 2019, 9th Biennial Conference on Innovative Data Systems Research,\n",
    "               Asilomar, CA, USA, January 13-16, 2019, Online Proceedings},\n",
    "  publisher = {www.cidrdb.org},\n",
    "  year      = {2019},\n",
    "  url       = {http://cidrdb.org/cidr2019/gongshow/abstracts/cidr2019\\_82.pdf},\n",
    "  timestamp = {Thu, 12 Mar 2020 00:00:00 +0100},\n",
    "  biburl    = {https://dblp.org/rec/conf/cidr/Shin19.bib},\n",
    "  bibsource = {dblp computer science bibliography, https://dblp.org}\n",
    "}\n"
  ],
  "dnadatastorageandnearmoleculeprocessingfortheyottabyteera": [
    "\n",
    "@inproceedings{DBLP:conf/cidr/StraussC19,\n",
    "  author    = {Karin Strauss and\n",
    "               Luis Ceze},\n",
    "  title     = {{DNA} Data Storage and Near-Molecule Processing for the Yottabyte\n",
    "               Era},\n",
    "  booktitle = {{CIDR} 2019, 9th Biennial Conference on Innovative Data Systems Research,\n",
    "               Asilomar, CA, USA, January 13-16, 2019, Online Proceedings},\n",
    "  publisher = {www.cidrdb.org},\n",
    "  year      = {2019},\n",
    "  timestamp = {Thu, 17 Jan 2019 00:00:00 +0100},\n",
    "  biburl    = {https://dblp.org/rec/conf/cidr/StraussC19.bib},\n",
    "  bibsource = {dblp computer science bibliography, https://dblp.org}\n",
    "}\n"
  ],
  "makingneuralnetworkoptimizerspractical": [
    "\n",
    "@inproceedings{DBLP:conf/cidr/Taft19,\n",
    "  author    = {Rebecca Taft},\n",
    "  title     = {Making Neural Network Optimizers Practical},\n",
    "  booktitle = {{CIDR} 2019, 9th Biennial Conference on Innovative Data Systems Research,\n",
    "               Asilomar, CA, USA, January 13-16, 2019, Online Proceedings},\n",
    "  publisher = {www.cidrdb.org},\n",
    "  year      = {2019},\n",
    "  url       = {http://cidrdb.org/cidr2019/gongshow/abstracts/cidr2019\\_43.pdf},\n",
    "  timestamp = {Thu, 12 Mar 2020 00:00:00 +0100},\n",
    "  biburl    = {https://dblp.org/rec/conf/cidr/Taft19.bib},\n",
    "  bibsource = {dblp computer science bibliography, https://dblp.org}\n",
    "}\n"
  ],
  "kyrixinteractivevisualdataexplorationatscale": [
    "\n",
    "@inproceedings{DBLP:conf/cidr/TaoLDCS19,\n",
    "  author    = {Wenbo Tao and\n",
    "               Xiaoyu Liu and\n",
    "               {\\c{C}}agatay Demiralp and\n",
    "               Remco Chang and\n",
    "               Michael Stonebraker},\n",
    "  title     = {Kyrix: Interactive Visual Data Exploration at Scale},\n",
    "  booktitle = {{CIDR} 2019, 9th Biennial Conference on Innovative Data Systems Research,\n",
    "               Asilomar, CA, USA, January 13-16, 2019, Online Proceedings},\n",
    "  publisher = {www.cidrdb.org},\n",
    "  year      = {2019},\n",
    "  url       = {http://cidrdb.org/cidr2019/papers/p70-tao-cidr19.pdf},\n",
    "  timestamp = {Thu, 12 Mar 2020 00:00:00 +0100},\n",
    "  biburl    = {https://dblp.org/rec/conf/cidr/TaoLDCS19.bib},\n",
    "  bibsource = {dblp computer science bibliography, https://dblp.org}\n",
    "}\n"
  ],
  "itemsuggestadatamanagementplatformformachinelearnedrankingservices": [
    "\n",
    "@inproceedings{DBLP:conf/cidr/TataPCC19,\n",
    "  author    = {Sandeep Tata and\n",
    "               Vlad Panait and\n",
    "               Suming J. Chen and\n",
    "               Mike Colagrosso},\n",
    "  title     = {ItemSuggest: {A} Data Management Platform for Machine Learned Ranking\n",
    "               Services},\n",
    "  booktitle = {{CIDR} 2019, 9th Biennial Conference on Innovative Data Systems Research,\n",
    "               Asilomar, CA, USA, January 13-16, 2019, Online Proceedings},\n",
    "  publisher = {www.cidrdb.org},\n",
    "  year      = {2019},\n",
    "  url       = {http://cidrdb.org/cidr2019/papers/p29-tata-cidr19.pdf},\n",
    "  timestamp = {Mon, 24 Aug 2020 01:00:00 +0200},\n",
    "  biburl    = {https://dblp.org/rec/conf/cidr/TataPCC19.bib},\n",
    "  bibsource = {dblp computer science bibliography, https://dblp.org}\n",
    "}\n"
  ],
  "toolsforadvancedtimeseriesanalyticsenablingthefuture": [
    "\n",
    "@inproceedings{DBLP:conf/cidr/Tatbul19,\n",
    "  author    = {Nesime Tatbul},\n",
    "  title     = {Tools for Advanced Time Series Analytics: Enabling the Future},\n",
    "  booktitle = {{CIDR} 2019, 9th Biennial Conference on Innovative Data Systems Research,\n",
    "               Asilomar, CA, USA, January 13-16, 2019, Online Proceedings},\n",
    "  publisher = {www.cidrdb.org},\n",
    "  year      = {2019},\n",
    "  url       = {http://cidrdb.org/cidr2019/gongshow/abstracts/cidr2019\\_162.pdf},\n",
    "  timestamp = {Thu, 12 Mar 2020 00:00:00 +0100},\n",
    "  biburl    = {https://dblp.org/rec/conf/cidr/Tatbul19.bib},\n",
    "  bibsource = {dblp computer science bibliography, https://dblp.org}\n",
    "}\n"
  ],
  "datavocalizationwithcicerodb": [
    "\n",
    "@inproceedings{DBLP:conf/cidr/Trummer19,\n",
    "  author    = {Immanuel Trummer},\n",
    "  title     = {Data Vocalization with CiceroDB},\n",
    "  booktitle = {{CIDR} 2019, 9th Biennial Conference on Innovative Data Systems Research,\n",
    "               Asilomar, CA, USA, January 13-16, 2019, Online Proceedings},\n",
    "  publisher = {www.cidrdb.org},\n",
    "  year      = {2019},\n",
    "  url       = {http://cidrdb.org/cidr2019/papers/p39-trummer-cidr19.pdf},\n",
    "  timestamp = {Thu, 12 Mar 2020 00:00:00 +0100},\n",
    "  biburl    = {https://dblp.org/rec/conf/cidr/Trummer19.bib},\n",
    "  bibsource = {dblp computer science bibliography, https://dblp.org}\n",
    "}\n"
  ],
  "crazyideadatabasesunicodereinforcementlearningresearchcidr": [
    "\n",
    "@inproceedings{DBLP:conf/cidr/Wu19,\n",
    "  author    = {Eugene Wu},\n",
    "  title     = {Crazy Idea! Databases {\\unicode{10781}} Reinforcement-learning Research\n",
    "               {(CIDR2)}},\n",
    "  booktitle = {{CIDR} 2019, 9th Biennial Conference on Innovative Data Systems Research,\n",
    "               Asilomar, CA, USA, January 13-16, 2019, Online Proceedings},\n",
    "  publisher = {www.cidrdb.org},\n",
    "  year      = {2019},\n",
    "  url       = {http://cidrdb.org/cidr2019/gongshow/abstracts/cidr2019\\_16.pdf},\n",
    "  timestamp = {Thu, 12 Mar 2020 00:00:00 +0100},\n",
    "  biburl    = {https://dblp.org/rec/conf/cidr/Wu19.bib},\n",
    "  bibsource = {dblp computer science bibliography, https://dblp.org}\n",
    "}\n"
  ],
  "theendofthexdominanceindatabases": [
    "\n",
    "@inproceedings{DBLP:conf/cidr/Zhang19,\n",
    "  author    = {Huanchen Zhang},\n",
    "  title     = {The End of the x86 Dominance in Databases?},\n",
    "  booktitle = {{CIDR} 2019, 9th Biennial Conference on Innovative Data Systems Research,\n",
    "               Asilomar, CA, USA, January 13-16, 2019, Online Proceedings},\n",
    "  publisher = {www.cidrdb.org},\n",
    "  year      = {2019},\n",
    "  url       = {http://cidrdb.org/cidr2019/gongshow/abstracts/cidr2019\\_160.pdf},\n",
    "  timestamp = {Thu, 12 Mar 2020 00:00:00 +0100},\n",
    "  biburl    = {https://dblp.org/rec/conf/cidr/Zhang19.bib},\n",
    "  bibsource = {dblp computer science bibliography, https://dblp.org}\n",
    "}\n"
  ],
  "datapartitioningforinmemorysystemsmythschallengesandopportunities": [
    "\n",
    "@inproceedings{DBLP:conf/cidr/ZhangDP19,\n",
    "  author    = {Zuyu Zhang and\n",
    "               Harshad Deshmukh and\n",
    "               Jignesh M. Patel},\n",
    "  title     = {Data Partitioning for In-Memory Systems: Myths, Challenges, and Opportunities},\n",
    "  booktitle = {{CIDR} 2019, 9th Biennial Conference on Innovative Data Systems Research,\n",
    "               Asilomar, CA, USA, January 13-16, 2019, Online Proceedings},\n",
    "  publisher = {www.cidrdb.org},\n",
    "  year      = {2019},\n",
    "  url       = {http://cidrdb.org/cidr2019/papers/p133-zhang-cidr19.pdf},\n",
    "  timestamp = {Thu, 12 Mar 2020 00:00:00 +0100},\n",
    "  biburl    = {https://dblp.org/rec/conf/cidr/ZhangDP19.bib},\n",
    "  bibsource = {dblp computer science bibliography, https://dblp.org}\n",
    "}\n"
  ],
  "cidrthbiennialconferenceoninnovativedatasystemsresearchasilomarcausajanuaryonlineproceedings": [
    "\n",
    "@proceedings{DBLP:conf/cidr/2019,\n",
    "  title     = {{CIDR} 2019, 9th Biennial Conference on Innovative Data Systems Research,\n",
    "               Asilomar, CA, USA, January 13-16, 2019, Online Proceedings},\n",
    "  publisher = {www.cidrdb.org},\n",
    "  year      = {2019},\n",
    "  url       = {http://cidrdb.org/cidr2019/index.html},\n",
    "  timestamp = {Thu, 17 Jan 2019 00:00:00 +0100},\n",
    "  biburl    = {https://dblp.org/rec/conf/cidr/2019.bib},\n",
    "  bibsource = {dblp computer science bibliography, https://dblp.org}\n",
    "}\n"
  ]
}