{
  "inducingsuffixandlcparraysinexternalmemory": [
    "@inproceedings{DBLP:conf/alenex/BingmannFO13,\n",
    "  author    = {Timo Bingmann and\n",
    "               Johannes Fischer and\n",
    "               Vitaly Osipov},\n",
    "  editor    = {Peter Sanders and\n",
    "               Norbert Zeh},\n",
    "  title     = {Inducing Suffix and Lcp Arrays in External Memory},\n",
    "  booktitle = {Proceedings of the 15th Meeting on Algorithm Engineering and Experiments,\n",
    "               {ALENEX} 2013, New Orleans, Louisiana, USA, January 7, 2013},\n",
    "  pages     = {88--102},\n",
    "  publisher = {{SIAM}},\n",
    "  year      = {2013},\n",
    "  url       = {https://doi.org/10.1137/1.9781611972931.8},\n",
    "  doi       = {10.1137/1.9781611972931.8},\n",
    "  timestamp = {Fri, 19 May 2017 01:26:03 +0200},\n",
    "  biburl    = {https://dblp.org/rec/conf/alenex/BingmannFO13.bib},\n",
    "  bibsource = {dblp computer science bibliography, https://dblp.org}\n",
    "}\n"
  ],
  "computationaltopologyandnormalsurfacestheoreticalandexperimentalcomplexitybounds": [
    "\n",
    "@inproceedings{DBLP:conf/alenex/BurtonPS13,\n",
    "  author    = {Benjamin A. Burton and\n",
    "               Jo{\\~{a}}o Paix{\\~{a}}o and\n",
    "               Jonathan Spreer},\n",
    "  editor    = {Peter Sanders and\n",
    "               Norbert Zeh},\n",
    "  title     = {Computational topology and normal surfaces: Theoretical and experimental\n",
    "               complexity bounds},\n",
    "  booktitle = {Proceedings of the 15th Meeting on Algorithm Engineering and Experiments,\n",
    "               {ALENEX} 2013, New Orleans, Louisiana, USA, January 7, 2013},\n",
    "  pages     = {78--87},\n",
    "  publisher = {{SIAM}},\n",
    "  year      = {2013},\n",
    "  url       = {https://doi.org/10.1137/1.9781611972931.7},\n",
    "  doi       = {10.1137/1.9781611972931.7},\n",
    "  timestamp = {Fri, 27 Dec 2019 00:00:00 +0100},\n",
    "  biburl    = {https://dblp.org/rec/conf/alenex/BurtonPS13.bib},\n",
    "  bibsource = {dblp computer science bibliography, https://dblp.org}\n",
    "}\n"
  ],
  "onparallelizingmatrixmultiplicationbythecolumnrowmethod": [
    "\n",
    "@inproceedings{DBLP:conf/alenex/CampagnaKP13,\n",
    "  author    = {Andrea Campagna and\n",
    "               Konstantin Kutzkov and\n",
    "               Rasmus Pagh},\n",
    "  editor    = {Peter Sanders and\n",
    "               Norbert Zeh},\n",
    "  title     = {On parallelizing matrix multiplication by the column-row method},\n",
    "  booktitle = {Proceedings of the 15th Meeting on Algorithm Engineering and Experiments,\n",
    "               {ALENEX} 2013, New Orleans, Louisiana, USA, January 7, 2013},\n",
    "  pages     = {122--132},\n",
    "  publisher = {{SIAM}},\n",
    "  year      = {2013},\n",
    "  url       = {https://doi.org/10.1137/1.9781611972931.11},\n",
    "  doi       = {10.1137/1.9781611972931.11},\n",
    "  timestamp = {Fri, 19 May 2017 01:00:00 +0200},\n",
    "  biburl    = {https://dblp.org/rec/conf/alenex/CampagnaKP13.bib},\n",
    "  bibsource = {dblp computer science bibliography, https://dblp.org}\n",
    "}\n"
  ],
  "aminedgecostflowframeworkforcapacitatedcoveringproblems": [
    "\n",
    "@inproceedings{DBLP:conf/alenex/ChangK13,\n",
    "  author    = {Jessica Chang and\n",
    "               Samir Khuller},\n",
    "  editor    = {Peter Sanders and\n",
    "               Norbert Zeh},\n",
    "  title     = {A Min-Edge Cost Flow Framework for Capacitated Covering Problems},\n",
    "  booktitle = {Proceedings of the 15th Meeting on Algorithm Engineering and Experiments,\n",
    "               {ALENEX} 2013, New Orleans, Louisiana, USA, January 7, 2013},\n",
    "  pages     = {14--25},\n",
    "  publisher = {{SIAM}},\n",
    "  year      = {2013},\n",
    "  url       = {https://doi.org/10.1137/1.9781611972931.2},\n",
    "  doi       = {10.1137/1.9781611972931.2},\n",
    "  timestamp = {Fri, 19 May 2017 01:00:00 +0200},\n",
    "  biburl    = {https://dblp.org/rec/conf/alenex/ChangK13.bib},\n",
    "  bibsource = {dblp computer science bibliography, https://dblp.org}\n",
    "}\n"
  ],
  "onunifyingthespaceofmathscrlmboxsamplingalgorithms": [
    "\n",
    "@inproceedings{DBLP:conf/alenex/CormodeF13,\n",
    "  author    = {Graham Cormode and\n",
    "               Donatella Firmani},\n",
    "  editor    = {Peter Sanders and\n",
    "               Norbert Zeh},\n",
    "  title     = {On Unifying the Space of {\\(\\mathscr{l}\\)}\\({}_{\\mbox{0}}\\)-Sampling\n",
    "               Algorithms},\n",
    "  booktitle = {Proceedings of the 15th Meeting on Algorithm Engineering and Experiments,\n",
    "               {ALENEX} 2013, New Orleans, Louisiana, USA, January 7, 2013},\n",
    "  pages     = {163--172},\n",
    "  publisher = {{SIAM}},\n",
    "  year      = {2013},\n",
    "  url       = {https://doi.org/10.1137/1.9781611972931.14},\n",
    "  doi       = {10.1137/1.9781611972931.14},\n",
    "  timestamp = {Sat, 19 Oct 2019 01:00:00 +0200},\n",
    "  biburl    = {https://dblp.org/rec/conf/alenex/CormodeF13.bib},\n",
    "  bibsource = {dblp computer science bibliography, https://dblp.org}\n",
    "}\n"
  ],
  "fastpackedstringmatchingforshortpatterns": [
    "\n",
    "@inproceedings{DBLP:conf/alenex/FaroK13,\n",
    "  author    = {Simone Faro and\n",
    "               M. Oguzhan K{\\\"{u}}lekci},\n",
    "  editor    = {Peter Sanders and\n",
    "               Norbert Zeh},\n",
    "  title     = {Fast Packed String Matching for Short Patterns},\n",
    "  booktitle = {Proceedings of the 15th Meeting on Algorithm Engineering and Experiments,\n",
    "               {ALENEX} 2013, New Orleans, Louisiana, USA, January 7, 2013},\n",
    "  pages     = {113--121},\n",
    "  publisher = {{SIAM}},\n",
    "  year      = {2013},\n",
    "  url       = {https://doi.org/10.1137/1.9781611972931.10},\n",
    "  doi       = {10.1137/1.9781611972931.10},\n",
    "  timestamp = {Wed, 29 May 2019 01:00:00 +0200},\n",
    "  biburl    = {https://dblp.org/rec/conf/alenex/FaroK13.bib},\n",
    "  bibsource = {dblp computer science bibliography, https://dblp.org}\n",
    "}\n"
  ],
  "shortandsimplecycleseparatorsinplanargraphs": [
    "\n",
    "@inproceedings{DBLP:conf/alenex/Fox-EpsteinMPS13,\n",
    "  author    = {Eli Fox{-}Epstein and\n",
    "               Shay Mozes and\n",
    "               Phitchaya Mangpo Phothilimthana and\n",
    "               Christian Sommer},\n",
    "  editor    = {Peter Sanders and\n",
    "               Norbert Zeh},\n",
    "  title     = {Short and Simple Cycle Separators in Planar Graphs},\n",
    "  booktitle = {Proceedings of the 15th Meeting on Algorithm Engineering and Experiments,\n",
    "               {ALENEX} 2013, New Orleans, Louisiana, USA, January 7, 2013},\n",
    "  pages     = {26--40},\n",
    "  publisher = {{SIAM}},\n",
    "  year      = {2013},\n",
    "  url       = {https://doi.org/10.1137/1.9781611972931.3},\n",
    "  doi       = {10.1137/1.9781611972931.3},\n",
    "  timestamp = {Sun, 02 Jun 2019 01:00:00 +0200},\n",
    "  biburl    = {https://dblp.org/rec/conf/alenex/Fox-EpsteinMPS13.bib},\n",
    "  bibsource = {dblp computer science bibliography, https://dblp.org}\n",
    "}\n"
  ],
  "polynomialtimeconstructionofcontractionhierarchiesformulticriteriaobjectives": [
    "\n",
    "@inproceedings{DBLP:conf/alenex/FunkeS13,\n",
    "  author    = {Stefan Funke and\n",
    "               Sabine Storandt},\n",
    "  editor    = {Peter Sanders and\n",
    "               Norbert Zeh},\n",
    "  title     = {Polynomial-time construction of contraction hierarchies for multi-criteria\n",
    "               objectives},\n",
    "  booktitle = {Proceedings of the 15th Meeting on Algorithm Engineering and Experiments,\n",
    "               {ALENEX} 2013, New Orleans, Louisiana, USA, January 7, 2013},\n",
    "  pages     = {41--54},\n",
    "  publisher = {{SIAM}},\n",
    "  year      = {2013},\n",
    "  url       = {https://doi.org/10.1137/1.9781611972931.4},\n",
    "  doi       = {10.1137/1.9781611972931.4},\n",
    "  timestamp = {Fri, 19 May 2017 01:00:00 +0200},\n",
    "  biburl    = {https://dblp.org/rec/conf/alenex/FunkeS13.bib},\n",
    "  bibsource = {dblp computer science bibliography, https://dblp.org}\n",
    "}\n"
  ],
  "thecostofaddresstranslation": [
    "\n",
    "@inproceedings{DBLP:conf/alenex/JurkiewiczM13,\n",
    "  author    = {Tomasz Jurkiewicz and\n",
    "               Kurt Mehlhorn},\n",
    "  editor    = {Peter Sanders and\n",
    "               Norbert Zeh},\n",
    "  title     = {The cost of address translation},\n",
    "  booktitle = {Proceedings of the 15th Meeting on Algorithm Engineering and Experiments,\n",
    "               {ALENEX} 2013, New Orleans, Louisiana, USA, January 7, 2013},\n",
    "  pages     = {148--162},\n",
    "  publisher = {{SIAM}},\n",
    "  year      = {2013},\n",
    "  url       = {https://doi.org/10.1137/1.9781611972931.13},\n",
    "  doi       = {10.1137/1.9781611972931.13},\n",
    "  timestamp = {Fri, 19 May 2017 01:00:00 +0200},\n",
    "  biburl    = {https://dblp.org/rec/conf/alenex/JurkiewiczM13.bib},\n",
    "  bibsource = {dblp computer science bibliography, https://dblp.org}\n",
    "}\n"
  ],
  "lempelzivfactorizationsimplefastpractical": [
    "\n",
    "@inproceedings{DBLP:conf/alenex/KempaP13,\n",
    "  author    = {Dominik Kempa and\n",
    "               Simon J. Puglisi},\n",
    "  editor    = {Peter Sanders and\n",
    "               Norbert Zeh},\n",
    "  title     = {Lempel-Ziv factorization: Simple, fast, practical},\n",
    "  booktitle = {Proceedings of the 15th Meeting on Algorithm Engineering and Experiments,\n",
    "               {ALENEX} 2013, New Orleans, Louisiana, USA, January 7, 2013},\n",
    "  pages     = {103--112},\n",
    "  publisher = {{SIAM}},\n",
    "  year      = {2013},\n",
    "  url       = {https://doi.org/10.1137/1.9781611972931.9},\n",
    "  doi       = {10.1137/1.9781611972931.9},\n",
    "  timestamp = {Mon, 15 Jun 2020 01:00:00 +0200},\n",
    "  biburl    = {https://dblp.org/rec/conf/alenex/KempaP13.bib},\n",
    "  bibsource = {dblp computer science bibliography, https://dblp.org}\n",
    "}\n"
  ],
  "dkineticalphacomplexesandtheirimplementation": [
    "\n",
    "@inproceedings{DBLP:conf/alenex/KerberE13,\n",
    "  author    = {Michael Kerber and\n",
    "               Herbert Edelsbrunner},\n",
    "  editor    = {Peter Sanders and\n",
    "               Norbert Zeh},\n",
    "  title     = {3D kinetic alpha complexes and their implementation},\n",
    "  booktitle = {Proceedings of the 15th Meeting on Algorithm Engineering and Experiments,\n",
    "               {ALENEX} 2013, New Orleans, Louisiana, USA, January 7, 2013},\n",
    "  pages     = {70--77},\n",
    "  publisher = {{SIAM}},\n",
    "  year      = {2013},\n",
    "  url       = {https://doi.org/10.1137/1.9781611972931.6},\n",
    "  doi       = {10.1137/1.9781611972931.6},\n",
    "  timestamp = {Fri, 19 May 2017 01:00:00 +0200},\n",
    "  biburl    = {https://dblp.org/rec/conf/alenex/KerberE13.bib},\n",
    "  bibsource = {dblp computer science bibliography, https://dblp.org}\n",
    "}\n"
  ],
  "practicalbatchupdatableexternalhashingwithsorting": [
    "\n",
    "@inproceedings{DBLP:conf/alenex/LimAK13,\n",
    "  author    = {Hyeontaek Lim and\n",
    "               David G. Andersen and\n",
    "               Michael Kaminsky},\n",
    "  editor    = {Peter Sanders and\n",
    "               Norbert Zeh},\n",
    "  title     = {Practical Batch-Updatable External Hashing with Sorting},\n",
    "  booktitle = {Proceedings of the 15th Meeting on Algorithm Engineering and Experiments,\n",
    "               {ALENEX} 2013, New Orleans, Louisiana, USA, January 7, 2013},\n",
    "  pages     = {173--182},\n",
    "  publisher = {{SIAM}},\n",
    "  year      = {2013},\n",
    "  url       = {https://doi.org/10.1137/1.9781611972931.15},\n",
    "  doi       = {10.1137/1.9781611972931.15},\n",
    "  timestamp = {Fri, 19 May 2017 01:00:00 +0200},\n",
    "  biburl    = {https://dblp.org/rec/conf/alenex/LimAK13.bib},\n",
    "  bibsource = {dblp computer science bibliography, https://dblp.org}\n",
    "}\n"
  ],
  "efficientalgorithmsfordualizinglargescalehypergraphs": [
    "\n",
    "@inproceedings{DBLP:conf/alenex/MurakamiU13,\n",
    "  author    = {Keisuke Murakami and\n",
    "               Takeaki Uno},\n",
    "  editor    = {Peter Sanders and\n",
    "               Norbert Zeh},\n",
    "  title     = {Efficient algorithms for dualizing large-scale hypergraphs},\n",
    "  booktitle = {Proceedings of the 15th Meeting on Algorithm Engineering and Experiments,\n",
    "               {ALENEX} 2013, New Orleans, Louisiana, USA, January 7, 2013},\n",
    "  pages     = {1--13},\n",
    "  publisher = {{SIAM}},\n",
    "  year      = {2013},\n",
    "  url       = {https://doi.org/10.1137/1.9781611972931.1},\n",
    "  doi       = {10.1137/1.9781611972931.1},\n",
    "  timestamp = {Fri, 19 May 2017 01:00:00 +0200},\n",
    "  biburl    = {https://dblp.org/rec/conf/alenex/MurakamiU13.bib},\n",
    "  bibsource = {dblp computer science bibliography, https://dblp.org}\n",
    "}\n"
  ],
  "robustgossipbasedaggregationapracticalpointofview": [
    "\n",
    "@inproceedings{DBLP:conf/alenex/NiederbruckerG13,\n",
    "  author    = {Gerhard Niederbrucker and\n",
    "               Wilfried N. Gansterer},\n",
    "  editor    = {Peter Sanders and\n",
    "               Norbert Zeh},\n",
    "  title     = {Robust gossip-based aggregation: {A} practical point of view},\n",
    "  booktitle = {Proceedings of the 15th Meeting on Algorithm Engineering and Experiments,\n",
    "               {ALENEX} 2013, New Orleans, Louisiana, USA, January 7, 2013},\n",
    "  pages     = {133--147},\n",
    "  publisher = {{SIAM}},\n",
    "  year      = {2013},\n",
    "  url       = {https://doi.org/10.1137/1.9781611972931.12},\n",
    "  doi       = {10.1137/1.9781611972931.12},\n",
    "  timestamp = {Fri, 19 May 2017 01:00:00 +0200},\n",
    "  biburl    = {https://dblp.org/rec/conf/alenex/NiederbruckerG13.bib},\n",
    "  bibsource = {dblp computer science bibliography, https://dblp.org}\n",
    "}\n"
  ],
  "engineeringjavasdualpivotquicksortusingmalijan": [
    "\n",
    "@inproceedings{DBLP:conf/alenex/WildNRL13,\n",
    "  author    = {Sebastian Wild and\n",
    "               Markus E. Nebel and\n",
    "               Raphael Reitzig and\n",
    "               Ulrich Laube},\n",
    "  editor    = {Peter Sanders and\n",
    "               Norbert Zeh},\n",
    "  title     = {Engineering Java 7's Dual Pivot Quicksort Using MaLiJan},\n",
    "  booktitle = {Proceedings of the 15th Meeting on Algorithm Engineering and Experiments,\n",
    "               {ALENEX} 2013, New Orleans, Louisiana, USA, January 7, 2013},\n",
    "  pages     = {55--69},\n",
    "  publisher = {{SIAM}},\n",
    "  year      = {2013},\n",
    "  url       = {https://doi.org/10.1137/1.9781611972931.5},\n",
    "  doi       = {10.1137/1.9781611972931.5},\n",
    "  timestamp = {Wed, 14 Nov 2018 00:00:00 +0100},\n",
    "  biburl    = {https://dblp.org/rec/conf/alenex/WildNRL13.bib},\n",
    "  bibsource = {dblp computer science bibliography, https://dblp.org}\n",
    "}\n"
  ],
  "proceedingsofthethmeetingonalgorithmengineeringandexperimentsalenexneworleanslouisianausajanuary": [
    "\n",
    "@proceedings{DBLP:conf/alenex/2013,\n",
    "  editor    = {Peter Sanders and\n",
    "               Norbert Zeh},\n",
    "  title     = {Proceedings of the 15th Meeting on Algorithm Engineering and Experiments,\n",
    "               {ALENEX} 2013, New Orleans, Louisiana, USA, January 7, 2013},\n",
    "  publisher = {{SIAM}},\n",
    "  year      = {2013},\n",
    "  url       = {https://doi.org/10.1137/1.9781611972931},\n",
    "  doi       = {10.1137/1.9781611972931},\n",
    "  isbn      = {978-1-61197-253-5},\n",
    "  timestamp = {Fri, 19 May 2017 01:00:00 +0200},\n",
    "  biburl    = {https://dblp.org/rec/conf/alenex/2013.bib},\n",
    "  bibsource = {dblp computer science bibliography, https://dblp.org}\n",
    "}\n"
  ]
}